{
  "authorDailyContributionsMap": {
    "otonashixav": [
      {
        "insertions": 90,
        "deletions": 12,
        "date": "2019-08-19",
        "commitResults": [
          {
            "hash": "684f06ff076a733e19f05843e87be02a26fdd611",
            "message": "Level-1",
            "insertions": 27,
            "deletions": 2
          },
          {
            "hash": "fff1d2e63c654edab7b139b6ea560db105cb971a",
            "message": "Level-2",
            "insertions": 18,
            "deletions": 3
          },
          {
            "hash": "d2c4d0647647f12c53000d12d09d395252058e1d",
            "message": "Level-3",
            "insertions": 42,
            "deletions": 4
          },
          {
            "hash": "559b0ad1b62735e1bc9d308cddab2580f236eb67",
            "message": "Level-3 minor changes to style consistency and while loop",
            "insertions": 3,
            "deletions": 3
          }
        ]
      },
      {
        "insertions": 557,
        "deletions": 148,
        "date": "2019-08-25",
        "commitResults": [
          {
            "hash": "d3f3ae3addc6a2ca20bb8629b4edc58e2d8111de",
            "message": "Level-4 stuff; split tasks into 3 different types and redid command parsing",
            "insertions": 109,
            "deletions": 32
          },
          {
            "hash": "88d0a676092da8fbea4cdb898e79575d26e7f109",
            "message": "fixed the startup help message",
            "insertions": 7,
            "deletions": 1
          },
          {
            "hash": "eafdf0d76bc35094b8d4b6647cec2bb30565528d",
            "message": "added error handling and the necessary exceptions",
            "insertions": 259,
            "deletions": 89
          },
          {
            "hash": "dfcfd8ffa02503f52a6118532d8b1f9fcbfd0264",
            "message": "added persistent tasks; redid tasks slightly",
            "insertions": 182,
            "deletions": 26
          }
        ]
      },
      {
        "insertions": 0,
        "deletions": 3,
        "date": "2019-08-26",
        "commitResults": [
          {
            "hash": "ff226ae06b080ca8ca57c25b34a22d55cf51e9d7",
            "message": "removed erroneous local arraylist",
            "insertions": 0,
            "deletions": 3
          }
        ]
      },
      {
        "insertions": 26,
        "deletions": 13,
        "date": "2019-08-28",
        "commitResults": [
          {
            "hash": "132fa3308b7c5306dca60ad5f33c3b28da2e04a1",
            "message": "added datetime; temporary solution that will be rewritten when i switch commands to classes",
            "insertions": 26,
            "deletions": 13
          }
        ]
      },
      {
        "insertions": 28,
        "deletions": 1,
        "date": "2019-08-29",
        "commitResults": [
          {
            "hash": "791ed4e820081e24bc5eea06e8217f237d83927a",
            "message": "added delete command",
            "insertions": 28,
            "deletions": 1
          }
        ]
      },
      {
        "insertions": 22,
        "deletions": 2,
        "date": "2019-09-02",
        "commitResults": [
          {
            "hash": "268cf5b04f2a9170af45132c505ac10ad2c7877d",
            "message": "added find command",
            "insertions": 22,
            "deletions": 2
          }
        ]
      }
    ],
    "Jeffry Lum": []
  },
  "authorFinalContributionMap": {
    "otonashixav": 545,
    "Jeffry Lum": 1
  },
  "authorFileFormatContributionMap": {
    "otonashixav": {
      "java": 545,
      "gradle": 0,
      "css": 0,
      "fxml": 0
    },
    "Jeffry Lum": {
      "java": 1,
      "gradle": 0,
      "css": 0,
      "fxml": 0
    }
  },
  "authorContributionVariance": {
    "otonashixav": 25843.102,
    "Jeffry Lum": 0.0
  },
  "authorDisplayNameMap": {
    "otonashixav": "otonashixav",
    "Jeffry Lum": "Jeffry Lum"
  }
}
