[
  {
    "path": "src/main/java/Deadline.java",
    "fileType": "java",
    "lines": [
      {
        "lineNumber": 1,
        "author": {
          "gitId": "sevenmatt7"
        },
        "content": "import java.text.SimpleDateFormat;"
      },
      {
        "lineNumber": 2,
        "author": {
          "gitId": "sevenmatt7"
        },
        "content": "import java.util.Date;"
      },
      {
        "lineNumber": 3,
        "author": {
          "gitId": "sevenmatt7"
        },
        "content": ""
      },
      {
        "lineNumber": 4,
        "author": {
          "gitId": "sevenmatt7"
        },
        "content": "public class Deadline extends Task {"
      },
      {
        "lineNumber": 5,
        "author": {
          "gitId": "sevenmatt7"
        },
        "content": "    private static final SimpleDateFormat DATE_FORMAT \u003d new SimpleDateFormat(\"d/M/yyyy HHmm\");"
      },
      {
        "lineNumber": 6,
        "author": {
          "gitId": "sevenmatt7"
        },
        "content": ""
      },
      {
        "lineNumber": 7,
        "author": {
          "gitId": "sevenmatt7"
        },
        "content": "    private Date dateTime;"
      },
      {
        "lineNumber": 8,
        "author": {
          "gitId": "sevenmatt7"
        },
        "content": ""
      },
      {
        "lineNumber": 9,
        "author": {
          "gitId": "sevenmatt7"
        },
        "content": "    public Deadline(String description, String date_string) {"
      },
      {
        "lineNumber": 10,
        "author": {
          "gitId": "sevenmatt7"
        },
        "content": "        super(description);"
      },
      {
        "lineNumber": 11,
        "author": {
          "gitId": "sevenmatt7"
        },
        "content": "        try {"
      },
      {
        "lineNumber": 12,
        "author": {
          "gitId": "sevenmatt7"
        },
        "content": "            //The code you are trying to exception handle"
      },
      {
        "lineNumber": 13,
        "author": {
          "gitId": "sevenmatt7"
        },
        "content": "            this.dateTime \u003d DATE_FORMAT.parse(date_string);"
      },
      {
        "lineNumber": 14,
        "author": {
          "gitId": "sevenmatt7"
        },
        "content": "        }"
      },
      {
        "lineNumber": 15,
        "author": {
          "gitId": "sevenmatt7"
        },
        "content": "        catch (Exception e) {"
      },
      {
        "lineNumber": 16,
        "author": {
          "gitId": "sevenmatt7"
        },
        "content": "            //The handling for the code"
      },
      {
        "lineNumber": 17,
        "author": {
          "gitId": "sevenmatt7"
        },
        "content": "            System.out.println(\"Wrong date format.\");"
      },
      {
        "lineNumber": 18,
        "author": {
          "gitId": "sevenmatt7"
        },
        "content": "        }"
      },
      {
        "lineNumber": 19,
        "author": {
          "gitId": "sevenmatt7"
        },
        "content": ""
      },
      {
        "lineNumber": 20,
        "author": {
          "gitId": "sevenmatt7"
        },
        "content": "    }"
      },
      {
        "lineNumber": 21,
        "author": {
          "gitId": "sevenmatt7"
        },
        "content": ""
      },
      {
        "lineNumber": 22,
        "author": {
          "gitId": "sevenmatt7"
        },
        "content": "    @Override"
      },
      {
        "lineNumber": 23,
        "author": {
          "gitId": "sevenmatt7"
        },
        "content": "    public String toString() {"
      },
      {
        "lineNumber": 24,
        "author": {
          "gitId": "sevenmatt7"
        },
        "content": "        return String.format(\"[D]%s(by: %s)\", super.toString(), DATE_FORMAT.format(dateTime));"
      },
      {
        "lineNumber": 25,
        "author": {
          "gitId": "sevenmatt7"
        },
        "content": "    }"
      },
      {
        "lineNumber": 26,
        "author": {
          "gitId": "sevenmatt7"
        },
        "content": ""
      },
      {
        "lineNumber": 27,
        "author": {
          "gitId": "sevenmatt7"
        },
        "content": ""
      },
      {
        "lineNumber": 28,
        "author": {
          "gitId": "sevenmatt7"
        },
        "content": "    @Override"
      },
      {
        "lineNumber": 29,
        "author": {
          "gitId": "sevenmatt7"
        },
        "content": "    public String formatString() {"
      },
      {
        "lineNumber": 30,
        "author": {
          "gitId": "sevenmatt7"
        },
        "content": "        return String.format("
      },
      {
        "lineNumber": 31,
        "author": {
          "gitId": "sevenmatt7"
        },
        "content": "                \"D|%s|%s\", super.formatString(), DATE_FORMAT.format(dateTime));"
      },
      {
        "lineNumber": 32,
        "author": {
          "gitId": "sevenmatt7"
        },
        "content": "    }"
      },
      {
        "lineNumber": 33,
        "author": {
          "gitId": "sevenmatt7"
        },
        "content": ""
      },
      {
        "lineNumber": 34,
        "author": {
          "gitId": "sevenmatt7"
        },
        "content": "}"
      }
    ],
    "authorContributionMap": {
      "sevenmatt7": 34
    }
  },
  {
    "path": "src/main/java/Duke.java",
    "fileType": "java",
    "lines": [
      {
        "lineNumber": 1,
        "author": {
          "gitId": "sevenmatt7"
        },
        "content": "import java.io.BufferedWriter;"
      },
      {
        "lineNumber": 2,
        "author": {
          "gitId": "sevenmatt7"
        },
        "content": "import java.io.FileWriter;"
      },
      {
        "lineNumber": 3,
        "author": {
          "gitId": "sevenmatt7"
        },
        "content": "import java.io.IOException;"
      },
      {
        "lineNumber": 4,
        "author": {
          "gitId": "sevenmatt7"
        },
        "content": "import java.io.Writer;"
      },
      {
        "lineNumber": 5,
        "author": {
          "gitId": "-"
        },
        "content": "import java.util.Scanner;"
      },
      {
        "lineNumber": 6,
        "author": {
          "gitId": "sevenmatt7"
        },
        "content": "import java.util.ArrayList;"
      },
      {
        "lineNumber": 7,
        "author": {
          "gitId": "sevenmatt7"
        },
        "content": ""
      },
      {
        "lineNumber": 8,
        "author": {
          "gitId": "-"
        },
        "content": ""
      },
      {
        "lineNumber": 9,
        "author": {
          "gitId": "-"
        },
        "content": "public class Duke {"
      },
      {
        "lineNumber": 10,
        "author": {
          "gitId": "sevenmatt7"
        },
        "content": "    public static boolean isExit \u003d false;"
      },
      {
        "lineNumber": 11,
        "author": {
          "gitId": "sevenmatt7"
        },
        "content": "    private Storage storage;"
      },
      {
        "lineNumber": 12,
        "author": {
          "gitId": "sevenmatt7"
        },
        "content": "    private TaskList tasks;"
      },
      {
        "lineNumber": 13,
        "author": {
          "gitId": "sevenmatt7"
        },
        "content": "    private Ui ui;"
      },
      {
        "lineNumber": 14,
        "author": {
          "gitId": "sevenmatt7"
        },
        "content": ""
      },
      {
        "lineNumber": 15,
        "author": {
          "gitId": "sevenmatt7"
        },
        "content": "    public Duke(String filePath) throws IOException {  //constructor for the Duke Object"
      },
      {
        "lineNumber": 16,
        "author": {
          "gitId": "sevenmatt7"
        },
        "content": "        ui \u003d new Ui();"
      },
      {
        "lineNumber": 17,
        "author": {
          "gitId": "sevenmatt7"
        },
        "content": "        storage \u003d new Storage(filePath);"
      },
      {
        "lineNumber": 18,
        "author": {
          "gitId": "sevenmatt7"
        },
        "content": "//        try {"
      },
      {
        "lineNumber": 19,
        "author": {
          "gitId": "sevenmatt7"
        },
        "content": "            tasks \u003d new TaskList();"
      },
      {
        "lineNumber": 20,
        "author": {
          "gitId": "sevenmatt7"
        },
        "content": "//        } catch (DukeException e) {"
      },
      {
        "lineNumber": 21,
        "author": {
          "gitId": "sevenmatt7"
        },
        "content": "//            ui.showLoadingError();"
      },
      {
        "lineNumber": 22,
        "author": {
          "gitId": "sevenmatt7"
        },
        "content": "//            tasks \u003d new TaskList();"
      },
      {
        "lineNumber": 23,
        "author": {
          "gitId": "sevenmatt7"
        },
        "content": "//        }"
      },
      {
        "lineNumber": 24,
        "author": {
          "gitId": "sevenmatt7"
        },
        "content": ""
      },
      {
        "lineNumber": 25,
        "author": {
          "gitId": "sevenmatt7"
        },
        "content": "    }"
      },
      {
        "lineNumber": 26,
        "author": {
          "gitId": "-"
        },
        "content": ""
      },
      {
        "lineNumber": 27,
        "author": {
          "gitId": "sevenmatt7"
        },
        "content": "    public static void setExit() {"
      },
      {
        "lineNumber": 28,
        "author": {
          "gitId": "sevenmatt7"
        },
        "content": "        isExit \u003d true;"
      },
      {
        "lineNumber": 29,
        "author": {
          "gitId": "sevenmatt7"
        },
        "content": "    }"
      },
      {
        "lineNumber": 30,
        "author": {
          "gitId": "sevenmatt7"
        },
        "content": ""
      },
      {
        "lineNumber": 31,
        "author": {
          "gitId": "sevenmatt7"
        },
        "content": "    public void run() {"
      },
      {
        "lineNumber": 32,
        "author": {
          "gitId": "sevenmatt7"
        },
        "content": "        Ui.welcome();"
      },
      {
        "lineNumber": 33,
        "author": {
          "gitId": "sevenmatt7"
        },
        "content": "        while(!isExit) {"
      },
      {
        "lineNumber": 34,
        "author": {
          "gitId": "sevenmatt7"
        },
        "content": "            String userInput \u003d Ui.readCommand();"
      },
      {
        "lineNumber": 35,
        "author": {
          "gitId": "sevenmatt7"
        },
        "content": "            Parser.interpretCommand(userInput);"
      },
      {
        "lineNumber": 36,
        "author": {
          "gitId": "-"
        },
        "content": "        }"
      },
      {
        "lineNumber": 37,
        "author": {
          "gitId": "sevenmatt7"
        },
        "content": "        Ui.exit();"
      },
      {
        "lineNumber": 38,
        "author": {
          "gitId": "sevenmatt7"
        },
        "content": "    }"
      },
      {
        "lineNumber": 39,
        "author": {
          "gitId": "sevenmatt7"
        },
        "content": ""
      },
      {
        "lineNumber": 40,
        "author": {
          "gitId": "sevenmatt7"
        },
        "content": "    public static void main(String[] args) throws IOException {"
      },
      {
        "lineNumber": 41,
        "author": {
          "gitId": "sevenmatt7"
        },
        "content": "        new Duke(\"Tasks.txt\").run();"
      },
      {
        "lineNumber": 42,
        "author": {
          "gitId": "-"
        },
        "content": "    }"
      },
      {
        "lineNumber": 43,
        "author": {
          "gitId": "sevenmatt7"
        },
        "content": "//    public static void main(String[] args) throws IOException {"
      },
      {
        "lineNumber": 44,
        "author": {
          "gitId": "sevenmatt7"
        },
        "content": "//        ArrayList\u003cTask\u003e taskList \u003d new ArrayList\u003cTask\u003e();"
      },
      {
        "lineNumber": 45,
        "author": {
          "gitId": "sevenmatt7"
        },
        "content": "//"
      },
      {
        "lineNumber": 46,
        "author": {
          "gitId": "sevenmatt7"
        },
        "content": "//        String greeting \u003d \"Hello I\u0027m Duke \\nWhat can I do for you?\";"
      },
      {
        "lineNumber": 47,
        "author": {
          "gitId": "sevenmatt7"
        },
        "content": "//        String goodbye \u003d \"Bye. Hope to see you again soon!\";"
      },
      {
        "lineNumber": 48,
        "author": {
          "gitId": "sevenmatt7"
        },
        "content": "//        System.out.println(greeting);"
      },
      {
        "lineNumber": 49,
        "author": {
          "gitId": "sevenmatt7"
        },
        "content": "//        String input \u003d \"0\";"
      },
      {
        "lineNumber": 50,
        "author": {
          "gitId": "sevenmatt7"
        },
        "content": "//        Scanner reader \u003d new Scanner(System.in);  // Reading from System.in"
      },
      {
        "lineNumber": 51,
        "author": {
          "gitId": "sevenmatt7"
        },
        "content": "//"
      },
      {
        "lineNumber": 52,
        "author": {
          "gitId": "sevenmatt7"
        },
        "content": "//        while (!input.equals(\"bye\")) {  //while the input is not bye"
      },
      {
        "lineNumber": 53,
        "author": {
          "gitId": "sevenmatt7"
        },
        "content": "//            input \u003d reader.nextLine();"
      },
      {
        "lineNumber": 54,
        "author": {
          "gitId": "sevenmatt7"
        },
        "content": "//            FileWriter fw \u003d new FileWriter(\"Tasks.txt\");"
      },
      {
        "lineNumber": 55,
        "author": {
          "gitId": "sevenmatt7"
        },
        "content": "//            Writer output \u003d new BufferedWriter(fw);"
      },
      {
        "lineNumber": 56,
        "author": {
          "gitId": "sevenmatt7"
        },
        "content": "//            for (Task task : taskList) {"
      },
      {
        "lineNumber": 57,
        "author": {
          "gitId": "sevenmatt7"
        },
        "content": "//                output.write(task.toString() + \"\\n\");"
      },
      {
        "lineNumber": 58,
        "author": {
          "gitId": "sevenmatt7"
        },
        "content": "//            }"
      },
      {
        "lineNumber": 59,
        "author": {
          "gitId": "sevenmatt7"
        },
        "content": "//            output.close();"
      },
      {
        "lineNumber": 60,
        "author": {
          "gitId": "sevenmatt7"
        },
        "content": "//"
      },
      {
        "lineNumber": 61,
        "author": {
          "gitId": "sevenmatt7"
        },
        "content": "//            if (input.equals(\"bye\")) { //terminates the whole program"
      },
      {
        "lineNumber": 62,
        "author": {
          "gitId": "sevenmatt7"
        },
        "content": "//                break;"
      },
      {
        "lineNumber": 63,
        "author": {
          "gitId": "sevenmatt7"
        },
        "content": "//            } else if (input.equals(\"list\")) {  //prints out the whole list of tasks"
      },
      {
        "lineNumber": 64,
        "author": {
          "gitId": "sevenmatt7"
        },
        "content": "//                if (taskList.isEmpty()) {"
      },
      {
        "lineNumber": 65,
        "author": {
          "gitId": "sevenmatt7"
        },
        "content": "//                    System.out.println(\"You have no tasks in your current list.\");"
      },
      {
        "lineNumber": 66,
        "author": {
          "gitId": "sevenmatt7"
        },
        "content": "//                } else {"
      },
      {
        "lineNumber": 67,
        "author": {
          "gitId": "sevenmatt7"
        },
        "content": "//                    System.out.println(\"Here are the tasks in your list: \");"
      },
      {
        "lineNumber": 68,
        "author": {
          "gitId": "sevenmatt7"
        },
        "content": "//                    int idx \u003d 1;"
      },
      {
        "lineNumber": 69,
        "author": {
          "gitId": "sevenmatt7"
        },
        "content": "//                    for (Task task : taskList) {"
      },
      {
        "lineNumber": 70,
        "author": {
          "gitId": "sevenmatt7"
        },
        "content": "//                        System.out.println(idx + \". \" + task.toString());"
      },
      {
        "lineNumber": 71,
        "author": {
          "gitId": "sevenmatt7"
        },
        "content": "//                        idx +\u003d 1;"
      },
      {
        "lineNumber": 72,
        "author": {
          "gitId": "sevenmatt7"
        },
        "content": "//                    }"
      },
      {
        "lineNumber": 73,
        "author": {
          "gitId": "sevenmatt7"
        },
        "content": "//                }"
      },
      {
        "lineNumber": 74,
        "author": {
          "gitId": "sevenmatt7"
        },
        "content": "//            } else if (input.contains(\"done\")) {   //marks the task specified as done"
      },
      {
        "lineNumber": 75,
        "author": {
          "gitId": "sevenmatt7"
        },
        "content": "//                int idx \u003d Character.getNumericValue(input.charAt(5)) - 1;"
      },
      {
        "lineNumber": 76,
        "author": {
          "gitId": "sevenmatt7"
        },
        "content": "//                taskList.get(idx).setDone();"
      },
      {
        "lineNumber": 77,
        "author": {
          "gitId": "sevenmatt7"
        },
        "content": "//                System.out.println( \"Nice! I\u0027ve marked this task as done:\\n\\t\" + taskList.get(idx).toString());"
      },
      {
        "lineNumber": 78,
        "author": {
          "gitId": "sevenmatt7"
        },
        "content": "//            } else {  //adds the task typed out into the list"
      },
      {
        "lineNumber": 79,
        "author": {
          "gitId": "sevenmatt7"
        },
        "content": "//                if (input.startsWith(\"todo\")){"
      },
      {
        "lineNumber": 80,
        "author": {
          "gitId": "sevenmatt7"
        },
        "content": "//                    if (input.length() \u003d\u003d 4 ) {"
      },
      {
        "lineNumber": 81,
        "author": {
          "gitId": "sevenmatt7"
        },
        "content": "//                        System.out.println(\"OOPS!! The description of a todo cannot be empty!\");"
      },
      {
        "lineNumber": 82,
        "author": {
          "gitId": "sevenmatt7"
        },
        "content": "//                    } else {"
      },
      {
        "lineNumber": 83,
        "author": {
          "gitId": "sevenmatt7"
        },
        "content": "//                        TodoTask newTask \u003d new TodoTask(input.substring(5));"
      },
      {
        "lineNumber": 84,
        "author": {
          "gitId": "sevenmatt7"
        },
        "content": "//                        taskList.add(newTask);"
      },
      {
        "lineNumber": 85,
        "author": {
          "gitId": "sevenmatt7"
        },
        "content": "//                        System.out.println(\"added: \" + newTask.toString());"
      },
      {
        "lineNumber": 86,
        "author": {
          "gitId": "sevenmatt7"
        },
        "content": "//                    }"
      },
      {
        "lineNumber": 87,
        "author": {
          "gitId": "sevenmatt7"
        },
        "content": "//"
      },
      {
        "lineNumber": 88,
        "author": {
          "gitId": "sevenmatt7"
        },
        "content": "//                } else if (input.startsWith(\"deadline\")) {"
      },
      {
        "lineNumber": 89,
        "author": {
          "gitId": "sevenmatt7"
        },
        "content": "//                    String data \u003d input.substring(9);"
      },
      {
        "lineNumber": 90,
        "author": {
          "gitId": "sevenmatt7"
        },
        "content": "//                    String[] tokens \u003d  data.split(\"/by\");"
      },
      {
        "lineNumber": 91,
        "author": {
          "gitId": "sevenmatt7"
        },
        "content": "//                    Deadline newTask \u003d new Deadline(tokens[0], tokens[1]);"
      },
      {
        "lineNumber": 92,
        "author": {
          "gitId": "sevenmatt7"
        },
        "content": "//                    taskList.add(newTask);"
      },
      {
        "lineNumber": 93,
        "author": {
          "gitId": "sevenmatt7"
        },
        "content": "//                    System.out.println(\"added: \" + newTask.toString());"
      },
      {
        "lineNumber": 94,
        "author": {
          "gitId": "sevenmatt7"
        },
        "content": "//                } else if (input.startsWith(\"event\")) {"
      },
      {
        "lineNumber": 95,
        "author": {
          "gitId": "sevenmatt7"
        },
        "content": "//                    if (input.length() \u003d\u003d 5) {"
      },
      {
        "lineNumber": 96,
        "author": {
          "gitId": "sevenmatt7"
        },
        "content": "//                        System.out.println(\"OOPS!! You did not write down the activity for the event!\");"
      },
      {
        "lineNumber": 97,
        "author": {
          "gitId": "sevenmatt7"
        },
        "content": "//                    } else {"
      },
      {
        "lineNumber": 98,
        "author": {
          "gitId": "sevenmatt7"
        },
        "content": "//                        String data \u003d input.substring(6);"
      },
      {
        "lineNumber": 99,
        "author": {
          "gitId": "sevenmatt7"
        },
        "content": "//                        String[] tokens \u003d data.split(\"/\");"
      },
      {
        "lineNumber": 100,
        "author": {
          "gitId": "sevenmatt7"
        },
        "content": "//                        Event newTask \u003d new Event(tokens[0], tokens[1].substring(2));"
      },
      {
        "lineNumber": 101,
        "author": {
          "gitId": "sevenmatt7"
        },
        "content": "//                        taskList.add(newTask);"
      },
      {
        "lineNumber": 102,
        "author": {
          "gitId": "sevenmatt7"
        },
        "content": "//                        System.out.println(\"added: \" + newTask.toString());"
      },
      {
        "lineNumber": 103,
        "author": {
          "gitId": "sevenmatt7"
        },
        "content": "//                    }"
      },
      {
        "lineNumber": 104,
        "author": {
          "gitId": "sevenmatt7"
        },
        "content": "//                } else if (input.startsWith(\"delete\")) {"
      },
      {
        "lineNumber": 105,
        "author": {
          "gitId": "sevenmatt7"
        },
        "content": "//                    int idx \u003d Character.getNumericValue(input.charAt(7)) - 1;"
      },
      {
        "lineNumber": 106,
        "author": {
          "gitId": "sevenmatt7"
        },
        "content": "//                    System.out.println( \"Noted. I\u0027ve removed this task:\\n\\t\" + taskList.get(idx).toString());"
      },
      {
        "lineNumber": 107,
        "author": {
          "gitId": "sevenmatt7"
        },
        "content": "//                    taskList.remove(idx);"
      },
      {
        "lineNumber": 108,
        "author": {
          "gitId": "sevenmatt7"
        },
        "content": "//                } else if (input.startsWith(\"find\")) { //finds the tasks containing the search word"
      },
      {
        "lineNumber": 109,
        "author": {
          "gitId": "sevenmatt7"
        },
        "content": "//                    ArrayList\u003cString\u003e foundList \u003d new ArrayList\u003cString\u003e();"
      },
      {
        "lineNumber": 110,
        "author": {
          "gitId": "sevenmatt7"
        },
        "content": "//                    String searchTerm \u003d input.substring(5);"
      },
      {
        "lineNumber": 111,
        "author": {
          "gitId": "sevenmatt7"
        },
        "content": "//                    int idx \u003d 1;"
      },
      {
        "lineNumber": 112,
        "author": {
          "gitId": "sevenmatt7"
        },
        "content": "//                    for (Task task : taskList) {"
      },
      {
        "lineNumber": 113,
        "author": {
          "gitId": "sevenmatt7"
        },
        "content": "//                        if (task.toString().contains(searchTerm)) {"
      },
      {
        "lineNumber": 114,
        "author": {
          "gitId": "sevenmatt7"
        },
        "content": "//                            foundList.add(task.toString());"
      },
      {
        "lineNumber": 115,
        "author": {
          "gitId": "sevenmatt7"
        },
        "content": "//                        }"
      },
      {
        "lineNumber": 116,
        "author": {
          "gitId": "sevenmatt7"
        },
        "content": "//                    }"
      },
      {
        "lineNumber": 117,
        "author": {
          "gitId": "sevenmatt7"
        },
        "content": "//                    if (foundList.isEmpty()) {"
      },
      {
        "lineNumber": 118,
        "author": {
          "gitId": "sevenmatt7"
        },
        "content": "//                        System.out.println(\"I could not find any matching tasks.\");"
      },
      {
        "lineNumber": 119,
        "author": {
          "gitId": "sevenmatt7"
        },
        "content": "//                    } else {"
      },
      {
        "lineNumber": 120,
        "author": {
          "gitId": "sevenmatt7"
        },
        "content": "//                        System.out.println(\"Here are the matching tasks in your list:\\n\");"
      },
      {
        "lineNumber": 121,
        "author": {
          "gitId": "sevenmatt7"
        },
        "content": "//                        for (String str : foundList) {"
      },
      {
        "lineNumber": 122,
        "author": {
          "gitId": "sevenmatt7"
        },
        "content": "//                            System.out.println(idx + \". \" + str);"
      },
      {
        "lineNumber": 123,
        "author": {
          "gitId": "sevenmatt7"
        },
        "content": "//                            idx +\u003d 1;"
      },
      {
        "lineNumber": 124,
        "author": {
          "gitId": "sevenmatt7"
        },
        "content": "//                        }"
      },
      {
        "lineNumber": 125,
        "author": {
          "gitId": "sevenmatt7"
        },
        "content": "//                    }"
      },
      {
        "lineNumber": 126,
        "author": {
          "gitId": "sevenmatt7"
        },
        "content": "//                } else {"
      },
      {
        "lineNumber": 127,
        "author": {
          "gitId": "sevenmatt7"
        },
        "content": "//                    System.out.println(\"OOPS!! I don\u0027t know what that means!\");"
      },
      {
        "lineNumber": 128,
        "author": {
          "gitId": "sevenmatt7"
        },
        "content": "//                }"
      },
      {
        "lineNumber": 129,
        "author": {
          "gitId": "sevenmatt7"
        },
        "content": "//            }"
      },
      {
        "lineNumber": 130,
        "author": {
          "gitId": "sevenmatt7"
        },
        "content": "//        }"
      },
      {
        "lineNumber": 131,
        "author": {
          "gitId": "sevenmatt7"
        },
        "content": "//        System.out.println(goodbye);"
      },
      {
        "lineNumber": 132,
        "author": {
          "gitId": "sevenmatt7"
        },
        "content": "//    }"
      },
      {
        "lineNumber": 133,
        "author": {
          "gitId": "-"
        },
        "content": ""
      },
      {
        "lineNumber": 134,
        "author": {
          "gitId": "-"
        },
        "content": "}"
      }
    ],
    "authorContributionMap": {
      "sevenmatt7": 126,
      "-": 8
    }
  },
  {
    "path": "src/main/java/Event.java",
    "fileType": "java",
    "lines": [
      {
        "lineNumber": 1,
        "author": {
          "gitId": "sevenmatt7"
        },
        "content": "public class Event extends Task {"
      },
      {
        "lineNumber": 2,
        "author": {
          "gitId": "sevenmatt7"
        },
        "content": "    private String location;"
      },
      {
        "lineNumber": 3,
        "author": {
          "gitId": "sevenmatt7"
        },
        "content": ""
      },
      {
        "lineNumber": 4,
        "author": {
          "gitId": "sevenmatt7"
        },
        "content": "    public Event(String description, String location) {"
      },
      {
        "lineNumber": 5,
        "author": {
          "gitId": "sevenmatt7"
        },
        "content": "        super(description);"
      },
      {
        "lineNumber": 6,
        "author": {
          "gitId": "sevenmatt7"
        },
        "content": "        this.location \u003d location;"
      },
      {
        "lineNumber": 7,
        "author": {
          "gitId": "sevenmatt7"
        },
        "content": "    }"
      },
      {
        "lineNumber": 8,
        "author": {
          "gitId": "sevenmatt7"
        },
        "content": ""
      },
      {
        "lineNumber": 9,
        "author": {
          "gitId": "sevenmatt7"
        },
        "content": "    @Override"
      },
      {
        "lineNumber": 10,
        "author": {
          "gitId": "sevenmatt7"
        },
        "content": "    public String toString() {"
      },
      {
        "lineNumber": 11,
        "author": {
          "gitId": "sevenmatt7"
        },
        "content": "        return String.format(\"[E]%s(at:%s)\", super.toString(), location);"
      },
      {
        "lineNumber": 12,
        "author": {
          "gitId": "sevenmatt7"
        },
        "content": "    }"
      },
      {
        "lineNumber": 13,
        "author": {
          "gitId": "sevenmatt7"
        },
        "content": ""
      },
      {
        "lineNumber": 14,
        "author": {
          "gitId": "sevenmatt7"
        },
        "content": "    @Override"
      },
      {
        "lineNumber": 15,
        "author": {
          "gitId": "sevenmatt7"
        },
        "content": "    public String formatString() {"
      },
      {
        "lineNumber": 16,
        "author": {
          "gitId": "sevenmatt7"
        },
        "content": "        return String.format("
      },
      {
        "lineNumber": 17,
        "author": {
          "gitId": "sevenmatt7"
        },
        "content": "                \"E|%s|%s\", super.formatString(), location);"
      },
      {
        "lineNumber": 18,
        "author": {
          "gitId": "sevenmatt7"
        },
        "content": "    }"
      },
      {
        "lineNumber": 19,
        "author": {
          "gitId": "sevenmatt7"
        },
        "content": "}"
      }
    ],
    "authorContributionMap": {
      "sevenmatt7": 19
    }
  },
  {
    "path": "src/main/java/Parser.java",
    "fileType": "java",
    "lines": [
      {
        "lineNumber": 1,
        "author": {
          "gitId": "sevenmatt7"
        },
        "content": "public class Parser {"
      },
      {
        "lineNumber": 2,
        "author": {
          "gitId": "sevenmatt7"
        },
        "content": ""
      },
      {
        "lineNumber": 3,
        "author": {
          "gitId": "sevenmatt7"
        },
        "content": "    public static void interpretCommand(String input) {"
      },
      {
        "lineNumber": 4,
        "author": {
          "gitId": "sevenmatt7"
        },
        "content": "        if (input.equals(\"bye\")) {  //terminates the program"
      },
      {
        "lineNumber": 5,
        "author": {
          "gitId": "sevenmatt7"
        },
        "content": "            Duke.setExit();"
      },
      {
        "lineNumber": 6,
        "author": {
          "gitId": "sevenmatt7"
        },
        "content": "        } else if (input.equals(\"list\")) {  //prints out the whole list of tasks"
      },
      {
        "lineNumber": 7,
        "author": {
          "gitId": "sevenmatt7"
        },
        "content": "            TaskList.getList();"
      },
      {
        "lineNumber": 8,
        "author": {
          "gitId": "sevenmatt7"
        },
        "content": "        } else if (input.startsWith(\"done\")) {   //marks the task specified as done"
      },
      {
        "lineNumber": 9,
        "author": {
          "gitId": "sevenmatt7"
        },
        "content": "            TaskList.setDone(input);"
      },
      {
        "lineNumber": 10,
        "author": {
          "gitId": "sevenmatt7"
        },
        "content": "        } else if (input.startsWith(\"todo\")) {"
      },
      {
        "lineNumber": 11,
        "author": {
          "gitId": "sevenmatt7"
        },
        "content": "            String todoTask \u003d input.substring(5); //5th character is when the actual task is specified"
      },
      {
        "lineNumber": 12,
        "author": {
          "gitId": "sevenmatt7"
        },
        "content": "            TaskList.addTodo(todoTask);"
      },
      {
        "lineNumber": 13,
        "author": {
          "gitId": "sevenmatt7"
        },
        "content": "        } else if (input.startsWith(\"event\")) {"
      },
      {
        "lineNumber": 14,
        "author": {
          "gitId": "sevenmatt7"
        },
        "content": "            String eventActivity \u003d input.substring(6); //6th character is when the actual event is specified"
      },
      {
        "lineNumber": 15,
        "author": {
          "gitId": "sevenmatt7"
        },
        "content": "            TaskList.addEvent(eventActivity);"
      },
      {
        "lineNumber": 16,
        "author": {
          "gitId": "sevenmatt7"
        },
        "content": "        } else if (input.startsWith(\"deadline\")) {"
      },
      {
        "lineNumber": 17,
        "author": {
          "gitId": "sevenmatt7"
        },
        "content": "            String deadlineTask \u003d input.substring(9);"
      },
      {
        "lineNumber": 18,
        "author": {
          "gitId": "sevenmatt7"
        },
        "content": "            TaskList.addDeadline(deadlineTask);"
      },
      {
        "lineNumber": 19,
        "author": {
          "gitId": "sevenmatt7"
        },
        "content": "        } else if (input.startsWith(\"delete\")) {"
      },
      {
        "lineNumber": 20,
        "author": {
          "gitId": "sevenmatt7"
        },
        "content": "            int idx \u003d Character.getNumericValue(input.charAt(7)) - 1;"
      },
      {
        "lineNumber": 21,
        "author": {
          "gitId": "sevenmatt7"
        },
        "content": "            TaskList.deleteTask(idx);"
      },
      {
        "lineNumber": 22,
        "author": {
          "gitId": "sevenmatt7"
        },
        "content": "        } else if (input.startsWith(\"find\")) {"
      },
      {
        "lineNumber": 23,
        "author": {
          "gitId": "sevenmatt7"
        },
        "content": "            String searchTerm \u003d input.substring(5);"
      },
      {
        "lineNumber": 24,
        "author": {
          "gitId": "sevenmatt7"
        },
        "content": "            TaskList.getFoundlist(searchTerm);"
      },
      {
        "lineNumber": 25,
        "author": {
          "gitId": "sevenmatt7"
        },
        "content": "        } else {"
      },
      {
        "lineNumber": 26,
        "author": {
          "gitId": "sevenmatt7"
        },
        "content": "            System.out.println(\"OOPS! I don\u0027t know what that means!\");"
      },
      {
        "lineNumber": 27,
        "author": {
          "gitId": "sevenmatt7"
        },
        "content": "        }"
      },
      {
        "lineNumber": 28,
        "author": {
          "gitId": "sevenmatt7"
        },
        "content": "    }"
      },
      {
        "lineNumber": 29,
        "author": {
          "gitId": "sevenmatt7"
        },
        "content": ""
      },
      {
        "lineNumber": 30,
        "author": {
          "gitId": "sevenmatt7"
        },
        "content": "}"
      }
    ],
    "authorContributionMap": {
      "sevenmatt7": 30
    }
  },
  {
    "path": "src/main/java/Storage.java",
    "fileType": "java",
    "lines": [
      {
        "lineNumber": 1,
        "author": {
          "gitId": "sevenmatt7"
        },
        "content": "import java.io.BufferedWriter;"
      },
      {
        "lineNumber": 2,
        "author": {
          "gitId": "sevenmatt7"
        },
        "content": "import java.io.FileWriter;"
      },
      {
        "lineNumber": 3,
        "author": {
          "gitId": "sevenmatt7"
        },
        "content": "import java.io.IOException;"
      },
      {
        "lineNumber": 4,
        "author": {
          "gitId": "sevenmatt7"
        },
        "content": "import java.io.Writer;"
      },
      {
        "lineNumber": 5,
        "author": {
          "gitId": "sevenmatt7"
        },
        "content": ""
      },
      {
        "lineNumber": 6,
        "author": {
          "gitId": "sevenmatt7"
        },
        "content": "public class Storage {"
      },
      {
        "lineNumber": 7,
        "author": {
          "gitId": "sevenmatt7"
        },
        "content": ""
      },
      {
        "lineNumber": 8,
        "author": {
          "gitId": "sevenmatt7"
        },
        "content": "    public Storage (String filePath) throws IOException {"
      },
      {
        "lineNumber": 9,
        "author": {
          "gitId": "sevenmatt7"
        },
        "content": "        FileWriter fw \u003d new FileWriter(filePath);"
      },
      {
        "lineNumber": 10,
        "author": {
          "gitId": "sevenmatt7"
        },
        "content": "        Writer output \u003d new BufferedWriter(fw);"
      },
      {
        "lineNumber": 11,
        "author": {
          "gitId": "sevenmatt7"
        },
        "content": "//"
      },
      {
        "lineNumber": 12,
        "author": {
          "gitId": "sevenmatt7"
        },
        "content": "        output.close();"
      },
      {
        "lineNumber": 13,
        "author": {
          "gitId": "sevenmatt7"
        },
        "content": "    }"
      },
      {
        "lineNumber": 14,
        "author": {
          "gitId": "sevenmatt7"
        },
        "content": ""
      },
      {
        "lineNumber": 15,
        "author": {
          "gitId": "sevenmatt7"
        },
        "content": "}"
      }
    ],
    "authorContributionMap": {
      "sevenmatt7": 15
    }
  },
  {
    "path": "src/main/java/Task.java",
    "fileType": "java",
    "lines": [
      {
        "lineNumber": 1,
        "author": {
          "gitId": "sevenmatt7"
        },
        "content": "public class Task {"
      },
      {
        "lineNumber": 2,
        "author": {
          "gitId": "sevenmatt7"
        },
        "content": "    protected String description;"
      },
      {
        "lineNumber": 3,
        "author": {
          "gitId": "sevenmatt7"
        },
        "content": "    protected boolean isDone;"
      },
      {
        "lineNumber": 4,
        "author": {
          "gitId": "sevenmatt7"
        },
        "content": ""
      },
      {
        "lineNumber": 5,
        "author": {
          "gitId": "sevenmatt7"
        },
        "content": "    public Task(String description) {"
      },
      {
        "lineNumber": 6,
        "author": {
          "gitId": "sevenmatt7"
        },
        "content": "        this.description \u003d description;"
      },
      {
        "lineNumber": 7,
        "author": {
          "gitId": "sevenmatt7"
        },
        "content": "        this.isDone \u003d false;"
      },
      {
        "lineNumber": 8,
        "author": {
          "gitId": "sevenmatt7"
        },
        "content": "    }"
      },
      {
        "lineNumber": 9,
        "author": {
          "gitId": "sevenmatt7"
        },
        "content": ""
      },
      {
        "lineNumber": 10,
        "author": {
          "gitId": "sevenmatt7"
        },
        "content": "    public String getStatusIcon() {"
      },
      {
        "lineNumber": 11,
        "author": {
          "gitId": "sevenmatt7"
        },
        "content": "        return (isDone ? \"\\u2713\" : \"\\u2718\"); //return tick or X symbols"
      },
      {
        "lineNumber": 12,
        "author": {
          "gitId": "sevenmatt7"
        },
        "content": "    }"
      },
      {
        "lineNumber": 13,
        "author": {
          "gitId": "sevenmatt7"
        },
        "content": ""
      },
      {
        "lineNumber": 14,
        "author": {
          "gitId": "sevenmatt7"
        },
        "content": "    public void setDone() {"
      },
      {
        "lineNumber": 15,
        "author": {
          "gitId": "sevenmatt7"
        },
        "content": "        this.isDone \u003d true;"
      },
      {
        "lineNumber": 16,
        "author": {
          "gitId": "sevenmatt7"
        },
        "content": "    }"
      },
      {
        "lineNumber": 17,
        "author": {
          "gitId": "sevenmatt7"
        },
        "content": ""
      },
      {
        "lineNumber": 18,
        "author": {
          "gitId": "sevenmatt7"
        },
        "content": "    public void setDescription(String description) {"
      },
      {
        "lineNumber": 19,
        "author": {
          "gitId": "sevenmatt7"
        },
        "content": "        this.description \u003d description;"
      },
      {
        "lineNumber": 20,
        "author": {
          "gitId": "sevenmatt7"
        },
        "content": "    }"
      },
      {
        "lineNumber": 21,
        "author": {
          "gitId": "sevenmatt7"
        },
        "content": ""
      },
      {
        "lineNumber": 22,
        "author": {
          "gitId": "sevenmatt7"
        },
        "content": "    public String formatString() {"
      },
      {
        "lineNumber": 23,
        "author": {
          "gitId": "sevenmatt7"
        },
        "content": "        return String.format("
      },
      {
        "lineNumber": 24,
        "author": {
          "gitId": "sevenmatt7"
        },
        "content": "                \"%d|%s\", isDone ? true : false, description"
      },
      {
        "lineNumber": 25,
        "author": {
          "gitId": "sevenmatt7"
        },
        "content": "        );"
      },
      {
        "lineNumber": 26,
        "author": {
          "gitId": "sevenmatt7"
        },
        "content": "    }"
      },
      {
        "lineNumber": 27,
        "author": {
          "gitId": "sevenmatt7"
        },
        "content": ""
      },
      {
        "lineNumber": 28,
        "author": {
          "gitId": "sevenmatt7"
        },
        "content": "    @Override"
      },
      {
        "lineNumber": 29,
        "author": {
          "gitId": "sevenmatt7"
        },
        "content": "    public String toString() {"
      },
      {
        "lineNumber": 30,
        "author": {
          "gitId": "sevenmatt7"
        },
        "content": "        return String.format(\"[%s] %s\", getStatusIcon(), description);"
      },
      {
        "lineNumber": 31,
        "author": {
          "gitId": "sevenmatt7"
        },
        "content": "    }"
      },
      {
        "lineNumber": 32,
        "author": {
          "gitId": "sevenmatt7"
        },
        "content": ""
      },
      {
        "lineNumber": 33,
        "author": {
          "gitId": "sevenmatt7"
        },
        "content": "}"
      },
      {
        "lineNumber": 34,
        "author": {
          "gitId": "sevenmatt7"
        },
        "content": ""
      }
    ],
    "authorContributionMap": {
      "sevenmatt7": 34
    }
  },
  {
    "path": "src/main/java/TaskList.java",
    "fileType": "java",
    "lines": [
      {
        "lineNumber": 1,
        "author": {
          "gitId": "sevenmatt7"
        },
        "content": "import java.util.ArrayList;"
      },
      {
        "lineNumber": 2,
        "author": {
          "gitId": "sevenmatt7"
        },
        "content": ""
      },
      {
        "lineNumber": 3,
        "author": {
          "gitId": "sevenmatt7"
        },
        "content": "public class TaskList {"
      },
      {
        "lineNumber": 4,
        "author": {
          "gitId": "sevenmatt7"
        },
        "content": "    private static ArrayList\u003cTask\u003e taskList;"
      },
      {
        "lineNumber": 5,
        "author": {
          "gitId": "sevenmatt7"
        },
        "content": ""
      },
      {
        "lineNumber": 6,
        "author": {
          "gitId": "sevenmatt7"
        },
        "content": "     public TaskList() {"
      },
      {
        "lineNumber": 7,
        "author": {
          "gitId": "sevenmatt7"
        },
        "content": "         this.taskList \u003d new ArrayList\u003cTask\u003e();"
      },
      {
        "lineNumber": 8,
        "author": {
          "gitId": "sevenmatt7"
        },
        "content": "     }"
      },
      {
        "lineNumber": 9,
        "author": {
          "gitId": "sevenmatt7"
        },
        "content": ""
      },
      {
        "lineNumber": 10,
        "author": {
          "gitId": "sevenmatt7"
        },
        "content": "     public static void getList() {"
      },
      {
        "lineNumber": 11,
        "author": {
          "gitId": "sevenmatt7"
        },
        "content": "         if (taskList.isEmpty()) {"
      },
      {
        "lineNumber": 12,
        "author": {
          "gitId": "sevenmatt7"
        },
        "content": "             System.out.println(\"You have no tasks in your list.\");"
      },
      {
        "lineNumber": 13,
        "author": {
          "gitId": "sevenmatt7"
        },
        "content": "         } else {"
      },
      {
        "lineNumber": 14,
        "author": {
          "gitId": "sevenmatt7"
        },
        "content": "             System.out.println(\"Here are the tasks in your list: \");"
      },
      {
        "lineNumber": 15,
        "author": {
          "gitId": "sevenmatt7"
        },
        "content": "             int idx \u003d 1;"
      },
      {
        "lineNumber": 16,
        "author": {
          "gitId": "sevenmatt7"
        },
        "content": "             for (Task task : taskList) {"
      },
      {
        "lineNumber": 17,
        "author": {
          "gitId": "sevenmatt7"
        },
        "content": "                 System.out.println(idx + \". \" + task.toString());"
      },
      {
        "lineNumber": 18,
        "author": {
          "gitId": "sevenmatt7"
        },
        "content": "                 idx +\u003d 1;"
      },
      {
        "lineNumber": 19,
        "author": {
          "gitId": "sevenmatt7"
        },
        "content": "             }"
      },
      {
        "lineNumber": 20,
        "author": {
          "gitId": "sevenmatt7"
        },
        "content": "         }"
      },
      {
        "lineNumber": 21,
        "author": {
          "gitId": "sevenmatt7"
        },
        "content": "     }"
      },
      {
        "lineNumber": 22,
        "author": {
          "gitId": "sevenmatt7"
        },
        "content": ""
      },
      {
        "lineNumber": 23,
        "author": {
          "gitId": "sevenmatt7"
        },
        "content": "     public static void setDone(String input) {"
      },
      {
        "lineNumber": 24,
        "author": {
          "gitId": "sevenmatt7"
        },
        "content": "         int idx \u003d Character.getNumericValue(input.charAt(5)) - 1;"
      },
      {
        "lineNumber": 25,
        "author": {
          "gitId": "sevenmatt7"
        },
        "content": "         taskList.get(idx).setDone();"
      },
      {
        "lineNumber": 26,
        "author": {
          "gitId": "sevenmatt7"
        },
        "content": "         System.out.println( \"Nice! I\u0027ve marked this task as done:\\n\\t\" + taskList.get(idx).toString());"
      },
      {
        "lineNumber": 27,
        "author": {
          "gitId": "sevenmatt7"
        },
        "content": "     }"
      },
      {
        "lineNumber": 28,
        "author": {
          "gitId": "sevenmatt7"
        },
        "content": ""
      },
      {
        "lineNumber": 29,
        "author": {
          "gitId": "sevenmatt7"
        },
        "content": "     public static void addTodo(String input) {"
      },
      {
        "lineNumber": 30,
        "author": {
          "gitId": "sevenmatt7"
        },
        "content": "         if (input.length() \u003d\u003d 0 ) {"
      },
      {
        "lineNumber": 31,
        "author": {
          "gitId": "sevenmatt7"
        },
        "content": "             System.out.println(\"OOPS!! The description of a todo cannot be empty!\");"
      },
      {
        "lineNumber": 32,
        "author": {
          "gitId": "sevenmatt7"
        },
        "content": "         } else {"
      },
      {
        "lineNumber": 33,
        "author": {
          "gitId": "sevenmatt7"
        },
        "content": "             TodoTask newTask \u003d new TodoTask(input);"
      },
      {
        "lineNumber": 34,
        "author": {
          "gitId": "sevenmatt7"
        },
        "content": "             taskList.add(newTask);"
      },
      {
        "lineNumber": 35,
        "author": {
          "gitId": "sevenmatt7"
        },
        "content": "             System.out.println(\"added: \" + newTask.toString());"
      },
      {
        "lineNumber": 36,
        "author": {
          "gitId": "sevenmatt7"
        },
        "content": "         }"
      },
      {
        "lineNumber": 37,
        "author": {
          "gitId": "sevenmatt7"
        },
        "content": "     }"
      },
      {
        "lineNumber": 38,
        "author": {
          "gitId": "sevenmatt7"
        },
        "content": ""
      },
      {
        "lineNumber": 39,
        "author": {
          "gitId": "sevenmatt7"
        },
        "content": "     public static void addEvent(String input) {"
      },
      {
        "lineNumber": 40,
        "author": {
          "gitId": "sevenmatt7"
        },
        "content": "         if (input.length() \u003d\u003d 0) {"
      },
      {
        "lineNumber": 41,
        "author": {
          "gitId": "sevenmatt7"
        },
        "content": "             System.out.println(\"OOPS!! You did not write down the activity for the event!\");"
      },
      {
        "lineNumber": 42,
        "author": {
          "gitId": "sevenmatt7"
        },
        "content": "         } else {"
      },
      {
        "lineNumber": 43,
        "author": {
          "gitId": "sevenmatt7"
        },
        "content": "             String[] tokens \u003d input.split(\"/\");"
      },
      {
        "lineNumber": 44,
        "author": {
          "gitId": "sevenmatt7"
        },
        "content": "             Event newTask \u003d new Event(tokens[0], tokens[1].substring(2));"
      },
      {
        "lineNumber": 45,
        "author": {
          "gitId": "sevenmatt7"
        },
        "content": "             taskList.add(newTask);"
      },
      {
        "lineNumber": 46,
        "author": {
          "gitId": "sevenmatt7"
        },
        "content": "             System.out.println(\"added: \" + newTask.toString());"
      },
      {
        "lineNumber": 47,
        "author": {
          "gitId": "sevenmatt7"
        },
        "content": "         }"
      },
      {
        "lineNumber": 48,
        "author": {
          "gitId": "sevenmatt7"
        },
        "content": "     }"
      },
      {
        "lineNumber": 49,
        "author": {
          "gitId": "sevenmatt7"
        },
        "content": ""
      },
      {
        "lineNumber": 50,
        "author": {
          "gitId": "sevenmatt7"
        },
        "content": "     public static void addDeadline(String input) {"
      },
      {
        "lineNumber": 51,
        "author": {
          "gitId": "sevenmatt7"
        },
        "content": "         if (input.length() \u003d\u003d 0) {"
      },
      {
        "lineNumber": 52,
        "author": {
          "gitId": "sevenmatt7"
        },
        "content": "             System.out.println(\"OOPS!! You did not write the task that needs to be finished by the deadline!\");"
      },
      {
        "lineNumber": 53,
        "author": {
          "gitId": "sevenmatt7"
        },
        "content": "         } else {"
      },
      {
        "lineNumber": 54,
        "author": {
          "gitId": "sevenmatt7"
        },
        "content": "             String[] tokens \u003d input.split(\"/\");"
      },
      {
        "lineNumber": 55,
        "author": {
          "gitId": "sevenmatt7"
        },
        "content": "             Deadline newTask \u003d new Deadline(tokens[0], tokens[1].substring(2));"
      },
      {
        "lineNumber": 56,
        "author": {
          "gitId": "sevenmatt7"
        },
        "content": "             taskList.add(newTask);"
      },
      {
        "lineNumber": 57,
        "author": {
          "gitId": "sevenmatt7"
        },
        "content": "             System.out.println(\"added: \" + newTask.toString());"
      },
      {
        "lineNumber": 58,
        "author": {
          "gitId": "sevenmatt7"
        },
        "content": "         }"
      },
      {
        "lineNumber": 59,
        "author": {
          "gitId": "sevenmatt7"
        },
        "content": "     }"
      },
      {
        "lineNumber": 60,
        "author": {
          "gitId": "sevenmatt7"
        },
        "content": ""
      },
      {
        "lineNumber": 61,
        "author": {
          "gitId": "sevenmatt7"
        },
        "content": "     public static void deleteTask(int idx) {"
      },
      {
        "lineNumber": 62,
        "author": {
          "gitId": "sevenmatt7"
        },
        "content": "         System.out.println( \"Noted. I\u0027ve removed this task:\\n\\t\" + taskList.get(idx).toString());"
      },
      {
        "lineNumber": 63,
        "author": {
          "gitId": "sevenmatt7"
        },
        "content": "         taskList.remove(idx);"
      },
      {
        "lineNumber": 64,
        "author": {
          "gitId": "sevenmatt7"
        },
        "content": "     }"
      },
      {
        "lineNumber": 65,
        "author": {
          "gitId": "sevenmatt7"
        },
        "content": ""
      },
      {
        "lineNumber": 66,
        "author": {
          "gitId": "sevenmatt7"
        },
        "content": "     public static void getFoundlist(String searchTerm) {"
      },
      {
        "lineNumber": 67,
        "author": {
          "gitId": "sevenmatt7"
        },
        "content": "         ArrayList\u003cString\u003e foundList \u003d new ArrayList\u003cString\u003e();"
      },
      {
        "lineNumber": 68,
        "author": {
          "gitId": "sevenmatt7"
        },
        "content": "         int idx \u003d 1;"
      },
      {
        "lineNumber": 69,
        "author": {
          "gitId": "sevenmatt7"
        },
        "content": "         for (Task task : taskList) {"
      },
      {
        "lineNumber": 70,
        "author": {
          "gitId": "sevenmatt7"
        },
        "content": "             if (task.toString().contains(searchTerm)) {"
      },
      {
        "lineNumber": 71,
        "author": {
          "gitId": "sevenmatt7"
        },
        "content": "                 foundList.add(task.toString());"
      },
      {
        "lineNumber": 72,
        "author": {
          "gitId": "sevenmatt7"
        },
        "content": "             }"
      },
      {
        "lineNumber": 73,
        "author": {
          "gitId": "sevenmatt7"
        },
        "content": "         }"
      },
      {
        "lineNumber": 74,
        "author": {
          "gitId": "sevenmatt7"
        },
        "content": "         if (foundList.isEmpty()) {"
      },
      {
        "lineNumber": 75,
        "author": {
          "gitId": "sevenmatt7"
        },
        "content": "             System.out.println(\"I could not find any matching tasks.\");"
      },
      {
        "lineNumber": 76,
        "author": {
          "gitId": "sevenmatt7"
        },
        "content": "         } else {"
      },
      {
        "lineNumber": 77,
        "author": {
          "gitId": "sevenmatt7"
        },
        "content": "             System.out.println(\"Here are the matching tasks in your list:\\n\");"
      },
      {
        "lineNumber": 78,
        "author": {
          "gitId": "sevenmatt7"
        },
        "content": "             for (String str : foundList) {"
      },
      {
        "lineNumber": 79,
        "author": {
          "gitId": "sevenmatt7"
        },
        "content": "                 System.out.println(idx + \". \" + str);"
      },
      {
        "lineNumber": 80,
        "author": {
          "gitId": "sevenmatt7"
        },
        "content": "                 idx +\u003d 1;"
      },
      {
        "lineNumber": 81,
        "author": {
          "gitId": "sevenmatt7"
        },
        "content": "             }"
      },
      {
        "lineNumber": 82,
        "author": {
          "gitId": "sevenmatt7"
        },
        "content": "         }"
      },
      {
        "lineNumber": 83,
        "author": {
          "gitId": "sevenmatt7"
        },
        "content": ""
      },
      {
        "lineNumber": 84,
        "author": {
          "gitId": "sevenmatt7"
        },
        "content": "     }"
      },
      {
        "lineNumber": 85,
        "author": {
          "gitId": "sevenmatt7"
        },
        "content": ""
      },
      {
        "lineNumber": 86,
        "author": {
          "gitId": "sevenmatt7"
        },
        "content": "}"
      }
    ],
    "authorContributionMap": {
      "sevenmatt7": 86
    }
  },
  {
    "path": "src/main/java/TodoTask.java",
    "fileType": "java",
    "lines": [
      {
        "lineNumber": 1,
        "author": {
          "gitId": "sevenmatt7"
        },
        "content": "public class TodoTask extends Task {"
      },
      {
        "lineNumber": 2,
        "author": {
          "gitId": "sevenmatt7"
        },
        "content": ""
      },
      {
        "lineNumber": 3,
        "author": {
          "gitId": "sevenmatt7"
        },
        "content": "    public TodoTask(String description) {"
      },
      {
        "lineNumber": 4,
        "author": {
          "gitId": "sevenmatt7"
        },
        "content": "        super(description);"
      },
      {
        "lineNumber": 5,
        "author": {
          "gitId": "sevenmatt7"
        },
        "content": "    }"
      },
      {
        "lineNumber": 6,
        "author": {
          "gitId": "sevenmatt7"
        },
        "content": ""
      },
      {
        "lineNumber": 7,
        "author": {
          "gitId": "sevenmatt7"
        },
        "content": "    @Override"
      },
      {
        "lineNumber": 8,
        "author": {
          "gitId": "sevenmatt7"
        },
        "content": "    public String toString() {"
      },
      {
        "lineNumber": 9,
        "author": {
          "gitId": "sevenmatt7"
        },
        "content": "        return String.format(\"[T]%s\", super.toString());"
      },
      {
        "lineNumber": 10,
        "author": {
          "gitId": "sevenmatt7"
        },
        "content": "    }"
      },
      {
        "lineNumber": 11,
        "author": {
          "gitId": "sevenmatt7"
        },
        "content": ""
      },
      {
        "lineNumber": 12,
        "author": {
          "gitId": "sevenmatt7"
        },
        "content": "    @Override"
      },
      {
        "lineNumber": 13,
        "author": {
          "gitId": "sevenmatt7"
        },
        "content": "    public String formatString() {"
      },
      {
        "lineNumber": 14,
        "author": {
          "gitId": "sevenmatt7"
        },
        "content": "        return String.format("
      },
      {
        "lineNumber": 15,
        "author": {
          "gitId": "sevenmatt7"
        },
        "content": "                \"T|%s\", super.formatString());"
      },
      {
        "lineNumber": 16,
        "author": {
          "gitId": "sevenmatt7"
        },
        "content": "    }"
      },
      {
        "lineNumber": 17,
        "author": {
          "gitId": "sevenmatt7"
        },
        "content": "}"
      }
    ],
    "authorContributionMap": {
      "sevenmatt7": 17
    }
  },
  {
    "path": "src/main/java/Ui.java",
    "fileType": "java",
    "lines": [
      {
        "lineNumber": 1,
        "author": {
          "gitId": "sevenmatt7"
        },
        "content": "import java.util.Scanner;"
      },
      {
        "lineNumber": 2,
        "author": {
          "gitId": "sevenmatt7"
        },
        "content": ""
      },
      {
        "lineNumber": 3,
        "author": {
          "gitId": "sevenmatt7"
        },
        "content": "public class Ui {"
      },
      {
        "lineNumber": 4,
        "author": {
          "gitId": "sevenmatt7"
        },
        "content": ""
      },
      {
        "lineNumber": 5,
        "author": {
          "gitId": "sevenmatt7"
        },
        "content": ""
      },
      {
        "lineNumber": 6,
        "author": {
          "gitId": "sevenmatt7"
        },
        "content": "    public static void welcome() {"
      },
      {
        "lineNumber": 7,
        "author": {
          "gitId": "sevenmatt7"
        },
        "content": "        System.out.println(\"Hello I\u0027m Duke \\nWhat can I do for you?\");"
      },
      {
        "lineNumber": 8,
        "author": {
          "gitId": "sevenmatt7"
        },
        "content": "    }"
      },
      {
        "lineNumber": 9,
        "author": {
          "gitId": "sevenmatt7"
        },
        "content": ""
      },
      {
        "lineNumber": 10,
        "author": {
          "gitId": "sevenmatt7"
        },
        "content": "    public static void exit () {"
      },
      {
        "lineNumber": 11,
        "author": {
          "gitId": "sevenmatt7"
        },
        "content": "        System.out.println(\"Bye! Hope to see you again soon!\");"
      },
      {
        "lineNumber": 12,
        "author": {
          "gitId": "sevenmatt7"
        },
        "content": "    }"
      },
      {
        "lineNumber": 13,
        "author": {
          "gitId": "sevenmatt7"
        },
        "content": ""
      },
      {
        "lineNumber": 14,
        "author": {
          "gitId": "sevenmatt7"
        },
        "content": "    public static String readCommand() {"
      },
      {
        "lineNumber": 15,
        "author": {
          "gitId": "sevenmatt7"
        },
        "content": "        Scanner reader \u003d new Scanner(System.in);"
      },
      {
        "lineNumber": 16,
        "author": {
          "gitId": "sevenmatt7"
        },
        "content": "        return reader.nextLine();"
      },
      {
        "lineNumber": 17,
        "author": {
          "gitId": "sevenmatt7"
        },
        "content": "    }"
      },
      {
        "lineNumber": 18,
        "author": {
          "gitId": "sevenmatt7"
        },
        "content": "}"
      }
    ],
    "authorContributionMap": {
      "sevenmatt7": 18
    }
  }
]
