{
  "authorDailyContributionsMap": {
    "JacobToresson": [
      {
        "insertions": 151,
        "deletions": 44,
        "date": "2019-08-22",
        "commitResults": [
          {
            "hash": "42bd9e27d2b36367c580ee6bcae5d83a83d77a14",
            "messageTitle": "Level-1: Greet, Echo, Exit",
            "messageBody": "",
            "insertions": 25,
            "deletions": 1
          },
          {
            "hash": "3ba351f27052fef30c96e4421c99851a64d8d8db",
            "messageTitle": "test",
            "messageBody": "",
            "insertions": 1,
            "deletions": 0
          },
          {
            "hash": "1bc62b763f2185015e15e6e14b673098174fe039",
            "messageTitle": "Level-1: Greet, Echo, Exit",
            "messageBody": "",
            "insertions": 2,
            "deletions": 1
          },
          {
            "hash": "817da9f209852728872f00115caae8c1c59912e2",
            "messageTitle": "Level-2: Add, List",
            "messageBody": "",
            "insertions": 2,
            "deletions": 0
          },
          {
            "hash": "6a32377a6e112ceef74380407b99095ebddf9788",
            "messageTitle": "Level-3: Mark as Done",
            "messageBody": "",
            "insertions": 2,
            "deletions": 0
          },
          {
            "hash": "5df423ef5e8d7c31a46dd9e22d32a98fdb873ff8",
            "messageTitle": "Level 2. Add, List",
            "messageBody": "",
            "insertions": 24,
            "deletions": 0
          },
          {
            "hash": "efe9c1d2af643dad62f5287301123a4a5fa08314",
            "messageTitle": "Level-3: Mark as Done",
            "messageBody": "",
            "insertions": 4,
            "deletions": 0
          },
          {
            "hash": "9f7aed69996c2837b24c88abe2c814bb473d3a41",
            "messageTitle": "Level-2: Add, List",
            "messageBody": "",
            "insertions": 9,
            "deletions": 1
          },
          {
            "hash": "3d1555ba6d4a9373c910e8266a154a03af080261",
            "messageTitle": "start of level 3",
            "messageBody": "",
            "insertions": 50,
            "deletions": 15
          },
          {
            "hash": "e97e6bc085c7f476f5ffbb35a9224f0bcecb94b5",
            "messageTitle": "Level-3: Mark as Done",
            "messageBody": "",
            "insertions": 32,
            "deletions": 26
          }
        ]
      },
      {
        "insertions": 115,
        "deletions": 162,
        "date": "2019-08-23",
        "commitResults": [
          {
            "hash": "079a8616d9f5b40f0314487dcc0e366b26b45f70",
            "messageTitle": "Delete Level3.java",
            "messageBody": "",
            "insertions": 0,
            "deletions": 10
          },
          {
            "hash": "dede3c291cb6c7abc44c2c861efed24197e05be0",
            "messageTitle": "Level 3. Mark as Done",
            "messageBody": "",
            "insertions": 1,
            "deletions": 1
          },
          {
            "hash": "2ea302e21254e99b8a1fca748164195eac503055",
            "messageTitle": "moving changes from level 1 file to duke file",
            "messageBody": "",
            "insertions": 19,
            "deletions": 1
          },
          {
            "hash": "58a24f8234a806a665c484c0e8b676fdd5fa1498",
            "messageTitle": "moving to duke file",
            "messageBody": "",
            "insertions": 1,
            "deletions": 0
          },
          {
            "hash": "c8ca7e543d78f39b8e18eeb83307ae8cb2af9b73",
            "messageTitle": "moving code from level1 file to duke",
            "messageBody": "",
            "insertions": 0,
            "deletions": 1
          },
          {
            "hash": "4f161ba65ec58209dace5361d9993d54129ffb59",
            "messageTitle": "Moving code from level 2 file to duke",
            "messageBody": "",
            "insertions": 40,
            "deletions": 15
          },
          {
            "hash": "68ce93d5c569fd4061e9e8d09b5c631921b68d7c",
            "messageTitle": "Revert \"Moving code from level 2 file to duke\"",
            "messageBody": "This reverts commit 4f161ba65ec58209dace5361d9993d54129ffb59.\n",
            "insertions": 15,
            "deletions": 40
          },
          {
            "hash": "ef3c7c73e5f0b9ae97acea06bd183c82d6b1739e",
            "messageTitle": "Cleaning files and moving code to right duke file",
            "messageBody": "",
            "insertions": 39,
            "deletions": 94
          }
        ]
      },
      {
        "insertions": 65,
        "deletions": 40,
        "date": "2019-08-24",
        "commitResults": [
          {
            "hash": "9e65977da06d46d55147ff217e1a8e2028522404",
            "messageTitle": "level 3 completed",
            "messageBody": "",
            "insertions": 63,
            "deletions": 37
          },
          {
            "hash": "6c387eb89f71b926af21aaa300823582d793d311",
            "messageTitle": "level 3",
            "messageBody": "",
            "insertions": 1,
            "deletions": 0
          },
          {
            "hash": "c628fd12e741cb99ebb0f44e7bdb3ff2c9aa2925",
            "messageTitle": "final level 3",
            "messageBody": "",
            "insertions": 1,
            "deletions": 1
          },
          {
            "hash": "3087e130151746b216aea64dd346e8b30d60b5a1",
            "messageTitle": "Level 3 final",
            "messageBody": "",
            "insertions": 0,
            "deletions": 2
          }
        ]
      }
    ],
    "Jeffry Lum": []
  },
  "authorFinalContributionMap": {
    "JacobToresson": 91,
    "Jeffry Lum": 0
  },
  "authorFileTypeContributionMap": {
    "JacobToresson": {
      "java": 91,
      "gradle": 0,
      "css": 0,
      "fxml": 0
    },
    "Jeffry Lum": {
      "java": 0,
      "gradle": 0,
      "css": 0,
      "fxml": 0
    }
  },
  "authorContributionVariance": {
    "JacobToresson": 7705.3145,
    "Jeffry Lum": 0.0
  },
  "authorDisplayNameMap": {
    "JacobToresson": "JacobToresson",
    "Jeffry Lum": "Jeffry Lum"
  }
}
