{
  "authorDailyContributionsMap": {
    "0325961": [
      {
        "insertions": 94,
        "deletions": 394,
        "date": "2019-08-27",
        "commitResults": [
          {
            "hash": "b5479929d76f7b5434e789be084069b1a43c027f",
            "message": "level-1",
            "insertions": 11,
            "deletions": 341
          },
          {
            "hash": "f156dd38dfaf1b3c3667cfe4f6aea221716b9c7d",
            "message": "level-2",
            "insertions": 19,
            "deletions": 21
          },
          {
            "hash": "80c71a8ccca015a7f6eb8e43b9f6b4243a48388a",
            "message": "level-3",
            "insertions": 29,
            "deletions": 16
          },
          {
            "hash": "490f4771c5c01d37f7ac32ad8692691d3b4fb95d",
            "message": "level-4",
            "insertions": 35,
            "deletions": 16
          }
        ]
      },
      {
        "insertions": 184,
        "deletions": 131,
        "date": "2019-08-28",
        "commitResults": [
          {
            "hash": "f74d7135bbde98ec1dbbec85d21a09e5e835c02f",
            "message": "level-5",
            "insertions": 89,
            "deletions": 57
          },
          {
            "hash": "40f9c0a27225e3794088bbdb63a1ca4e140a8230",
            "message": "level-7 (haven\u0027t read from drive yet)",
            "insertions": 95,
            "deletions": 74
          }
        ]
      },
      {
        "insertions": 12,
        "deletions": 3,
        "date": "2019-09-02",
        "commitResults": [
          {
            "hash": "5d4aff1cec55da807a8c151e4f88cd7c6760839d",
            "message": "level-6",
            "insertions": 12,
            "deletions": 3
          }
        ]
      }
    ],
    "Michelle Toh": [
      {
        "insertions": 123,
        "deletions": 1,
        "date": "2019-08-25",
        "commitResults": [
          {
            "hash": "dc16932254c4a34e8474724bed1a2dd397f486b9",
            "message": "level 1 level2 level 3",
            "insertions": 123,
            "deletions": 1
          }
        ]
      },
      {
        "insertions": 313,
        "deletions": 71,
        "date": "2019-08-26",
        "commitResults": [
          {
            "hash": "577d05c6b56b5705fef5f6cbadc08a6f5a82e41c",
            "message": "level 3 (A-classes) DONE",
            "insertions": 44,
            "deletions": 4
          },
          {
            "hash": "2658b14d3e90cb43bf022ecaeb86b2a06aae6883",
            "message": "Level-4, A-Inheritance",
            "insertions": 122,
            "deletions": 1
          },
          {
            "hash": "bcd622407afebc489738642680e016c4eb84aceb",
            "message": "Level-5, A-Exceptions",
            "insertions": 118,
            "deletions": 45
          },
          {
            "hash": "87ea24d49a2c1fe30e40258a21729a51ad0b7713",
            "message": "level-5 2nd edit",
            "insertions": 29,
            "deletions": 21
          }
        ]
      }
    ],
    "Jeffry Lum": []
  },
  "authorFinalContributionMap": {
    "0325961": 119,
    "Michelle Toh": 9,
    "Jeffry Lum": 16
  },
  "authorFileFormatContributionMap": {
    "0325961": {
      "java": 119,
      "gradle": 0,
      "css": 0,
      "fxml": 0
    },
    "Michelle Toh": {
      "java": 8,
      "gradle": 1,
      "css": 0,
      "fxml": 0
    },
    "Jeffry Lum": {
      "java": 0,
      "gradle": 16,
      "css": 0,
      "fxml": 0
    }
  },
  "authorContributionVariance": {
    "0325961": 16690.023,
    "Michelle Toh": 8249.73,
    "Jeffry Lum": 0.0
  },
  "authorDisplayNameMap": {
    "0325961": "0325961",
    "Michelle Toh": "Michelle Toh",
    "Jeffry Lum": "Jeffry Lum"
  }
}
