{
  "authorDailyContributionsMap": {
    "LL-Pengfei": [
      {
        "insertions": 242,
        "deletions": 177,
        "date": "2019-08-28",
        "commitResults": [
          {
            "hash": "b445dc262fee1a969727ac5d19260e32eb43d85b",
            "messageTitle": "no message",
            "messageBody": "",
            "insertions": 1,
            "deletions": 1
          },
          {
            "hash": "3cf9a8919ad7f1593c91ab8db7a74e5efc5014b0",
            "messageTitle": "Level 1",
            "messageBody": "",
            "insertions": 21,
            "deletions": 0
          },
          {
            "hash": "63d7502ac358437d6ffff1b1e64d7f41c962b4e2",
            "messageTitle": "Level 2",
            "messageBody": "",
            "insertions": 26,
            "deletions": 2
          },
          {
            "hash": "b647b57df6abee65ddc0a5992424933cf4753a77",
            "messageTitle": "Level 3",
            "messageBody": "",
            "insertions": 61,
            "deletions": 12
          },
          {
            "hash": "c270884b98ff05d5c4b7170c25ad967bc90a0844",
            "messageTitle": "Level 4",
            "messageBody": "",
            "insertions": 84,
            "deletions": 11
          },
          {
            "hash": "f8e68a06553939599aec323c755c61fbf3ce35b8",
            "messageTitle": "Level 5",
            "messageBody": "",
            "insertions": 7,
            "deletions": 1
          },
          {
            "hash": "67acc7f31ee3aa5e811f09e97f0fae4f8bdf4a6b",
            "messageTitle": "Level 3 - redo (using a class to represent tasks)",
            "messageBody": "",
            "insertions": 42,
            "deletions": 150
          }
        ]
      },
      {
        "insertions": 300,
        "deletions": 46,
        "date": "2019-08-29",
        "commitResults": [
          {
            "hash": "273aa03568e8e762b55a66d0cd8082b7cfae1b32",
            "messageTitle": "Level 4 (redo) + Inheritance",
            "messageBody": "",
            "insertions": 74,
            "deletions": 10
          },
          {
            "hash": "9b551ccb596a5bc64e5b204561f00550d2814379",
            "messageTitle": "Level 5 redo (using exception) + exceptions",
            "messageBody": "",
            "insertions": 33,
            "deletions": 0
          },
          {
            "hash": "e36d396d2b34c856ca71dd8cf2af159655fc013f",
            "messageTitle": "level 7, copyright documentations added",
            "messageBody": "",
            "insertions": 97,
            "deletions": 6
          },
          {
            "hash": "2e74ef5ceefaf42572c2f8b1737c0bdcbf5ce645",
            "messageTitle": "level 7 corrected",
            "messageBody": "",
            "insertions": 12,
            "deletions": 19
          },
          {
            "hash": "b317884d352756d2cfde582b62c4642d244ae67f",
            "messageTitle": "Level 8...finally done haha almost 0 java knowledge \u0026\u0026 oop knowledge to the difficulty level of level-8 within 48 hours.... too tired already next time shouldn\u0027t overload with so many mods, bearly got time to study everything",
            "messageBody": "",
            "insertions": 84,
            "deletions": 11
          }
        ]
      },
      {
        "insertions": 12,
        "deletions": 18,
        "date": "2019-08-30",
        "commitResults": [
          {
            "hash": "0e10fa1bb6fedcc998443c944a4e32ab85810b7d",
            "messageTitle": "cleaned codes up, add authorship tag",
            "messageBody": "",
            "insertions": 10,
            "deletions": 17
          },
          {
            "hash": "f6ca8ddf9a7ca0b83ed14a40f5ea35ee365e55a0",
            "messageTitle": "tut01 notes updated",
            "messageBody": "",
            "insertions": 2,
            "deletions": 1
          }
        ]
      },
      {
        "insertions": 120,
        "deletions": 18,
        "date": "2019-09-02",
        "commitResults": [
          {
            "hash": "e94b1704b9dffc3a71940eb50ca95af52c731335",
            "messageTitle": "used arraylist, a-collections accomplished, ready to be tagged after merging back with master branch",
            "messageBody": "",
            "insertions": 15,
            "deletions": 12
          },
          {
            "hash": "dd7cc3507f682c6f1cd7847ffe20fc0f8905f1d5",
            "messageTitle": "level-6 done, together with a-collections, ready to be tagged Level-6 \u0026\u0026 A-Collections after merging with the master branch",
            "messageBody": "",
            "insertions": 15,
            "deletions": 2
          },
          {
            "hash": "86aeb358782a7b4dcdd270ad9e166a857bf935af",
            "messageTitle": "Level 9 done. Ready to engage merge operation upon merging master with level 6. Energize.",
            "messageBody": "",
            "insertions": 12,
            "deletions": 1
          },
          {
            "hash": "2a1bd08ec9dd64b29b492c7c36c1eebdc6440d53",
            "messageTitle": "1. refactorised; 2. added comment at the top for each class for brief description; 3. in main class (Duke.class) added a list of all the functionalities and capabilities that this programme can provide to keep track",
            "messageBody": "",
            "insertions": 78,
            "deletions": 2
          },
          {
            "hash": "15b889fe5037a19b57ba9a7c14139c4d7f05e05d",
            "messageTitle": "Delete _colors.css",
            "messageBody": "",
            "insertions": 0,
            "deletions": 0
          },
          {
            "hash": "e8a3db9f108abf63d495e8e05b6f52dba3dfcabe",
            "messageTitle": "Delete style.css",
            "messageBody": "",
            "insertions": 0,
            "deletions": 1
          }
        ]
      },
      {
        "insertions": 5,
        "deletions": 1,
        "date": "2019-09-03",
        "commitResults": [
          {
            "hash": "70ec7204c55fc8cafb72e81f9d730619963fae23",
            "messageTitle": "trivial bug fix; text ui testing implemented, allowing io redirection technique to semi-automate testing of Duke - updated 20190903 13:22",
            "messageBody": "",
            "insertions": 1,
            "deletions": 1
          },
          {
            "hash": "98f74642dbba23b81363fdb0c73ffe58bfca9ce3",
            "messageTitle": "main function comment block add in description of new functionality of text ui testing",
            "messageBody": "",
            "insertions": 4,
            "deletions": 0
          }
        ]
      },
      {
        "insertions": 151,
        "deletions": 88,
        "date": "2019-09-04",
        "commitResults": [
          {
            "hash": "06eec152639e86ec18eeaba126fcc850e6ac30ac",
            "messageTitle": "Ui and Storage implemented (Ui not yet fully completed), Tasklist \u0026 Parser not yet done. Will package things up at the end. This is the stable version (tested, okay, can compile, can run correctly).",
            "messageBody": "",
            "insertions": 104,
            "deletions": 56
          },
          {
            "hash": "b05d59175528bcf094938a158e24389c703810b9",
            "messageTitle": "intermediate update (list+storage) - more oop - latest version as of 20190904",
            "messageBody": "",
            "insertions": 37,
            "deletions": 23
          },
          {
            "hash": "ea6e32e765565d839d6c3927a11eed6968aaa808",
            "messageTitle": "intermediate update - 20190904 21:26 ui storage duke update",
            "messageBody": "",
            "insertions": 10,
            "deletions": 9
          }
        ]
      },
      {
        "insertions": 286,
        "deletions": 205,
        "date": "2019-09-05",
        "commitResults": [
          {
            "hash": "c803d340921bbcf6564b4805c5ac36146a736078",
            "messageTitle": "A-MoreOOP implemented, 99% ready to be tagged",
            "messageBody": "",
            "insertions": 247,
            "deletions": 184
          },
          {
            "hash": "4c4bcdfaeb009c913c39b4d8b881580e807a2f76",
            "messageTitle": "more oop achieved, however, prob was encountered when attempting to package them up.... anyway, the tag requirement is now fulfilled",
            "messageBody": "",
            "insertions": 39,
            "deletions": 20
          },
          {
            "hash": "a9cd5e4b2227c10678ecec01215ee991ea506d0e",
            "messageTitle": "a-moreoop",
            "messageBody": "",
            "insertions": 0,
            "deletions": 1
          }
        ]
      },
      {
        "insertions": 1,
        "deletions": 1,
        "date": "2019-09-06",
        "commitResults": [
          {
            "hash": "31fccb3690f4378f2dd8c6864ebe5d95a9372b80",
            "messageTitle": "20190906 update (trivial)",
            "messageBody": "",
            "insertions": 1,
            "deletions": 1
          }
        ]
      },
      {
        "insertions": 280,
        "deletions": 100,
        "date": "2019-09-09",
        "commitResults": [
          {
            "hash": "4bb4212fd1885d929ba74e5ca371bc4e3c9f334e",
            "messageTitle": "a-junit, junit tsting, adding junit tests to test the behaviour of the code adding junit support to the project",
            "messageBody": "",
            "insertions": 22,
            "deletions": 0
          },
          {
            "hash": "c7f592b755725abf8f12a823d21ee5200bbaf156",
            "messageTitle": "adding in JavaDoc comments, intermediate update @2019/09/09 11:20AM",
            "messageBody": "",
            "insertions": 113,
            "deletions": 96
          },
          {
            "hash": "9a2a75c52fcb2354d5ee308704195bb6738788ff",
            "messageTitle": "a-javadoc implemented, awaiting to be merged back to master and be tagged",
            "messageBody": "",
            "insertions": 143,
            "deletions": 2
          },
          {
            "hash": "a8bef1da0c2cf437e24bf11fcdd34046966654a0",
            "messageTitle": "update branch-a-junit",
            "messageBody": "",
            "insertions": 1,
            "deletions": 1
          },
          {
            "hash": "a1f7cf58788b02416897b663cb09721ecac85324",
            "messageTitle": "get back to master branch (arbitrary update)",
            "messageBody": "",
            "insertions": 1,
            "deletions": 1
          }
        ]
      }
    ]
  },
  "authorFinalContributionMap": {
    "LL-Pengfei": 755
  },
  "authorFileTypeContributionMap": {
    "LL-Pengfei": {
      "java": 755,
      "gradle": 0,
      "css": 0,
      "fxml": 0
    }
  },
  "authorContributionVariance": {
    "LL-Pengfei": 24998.578
  },
  "authorDisplayNameMap": {
    "LL-Pengfei": "F09-2 ZHA..FEI"
  }
}
